[{"name": "datr", "value": "orfFZ4raBzVHo_KlTCi3KY27", "path": "/", "domain": ".instagram.com", "secure": true, "httpOnly": true, "expiry": 1775570851, "sameSite": "None"}, {"name": "mid", "value": "Z8W3owAEAAGkgnCcODbhfcAbyt0L", "path": "/", "domain": ".instagram.com", "secure": true, "httpOnly": false, "expiry": 1775570857, "sameSite": "None"}, {"name": "sessionid", "value": "72795790923%3AFoQTO0KG2BMEPJ%3A14%3AAYefhLbCs-WG51wH3nhwiQyz2COinAfqwkxyk8aqBQ", "path": "/", "domain": ".instagram.com", "secure": true, "httpOnly": true, "expiry": 1772546890, "sameSite": "None"}, {"name": "ig_did", "value": "5C3AD6CC-29E7-4944-86C7-E0932D2EFE11", "path": "/", "domain": ".instagram.com", "secure": true, "httpOnly": true, "expiry": 1772546890, "sameSite": "None"}, {"name": "ps_l", "value": "1", "path": "/", "domain": ".instagram.com", "secure": true, "httpOnly": true, "expiry": 1775570891, "sameSite": "Lax"}, {"name": "ps_n", "value": "1", "path": "/", "domain": ".instagram.com", "secure": true, "httpOnly": true, "expiry": 1775570891, "sameSite": "None"}, {"name": "wd", "value": "1307x656", "path": "/", "domain": ".instagram.com", "secure": true, "httpOnly": false, "expiry": 1741615694, "sameSite": "Lax"}, {"name": "csrftoken", "value": "IBPk2txGw57BOzJd-dVlyj", "path": "/", "domain": ".instagram.com", "secure": true, "httpOnly": false, "expiry": 1772460500, "sameSite": "None"}, {"name": "rur", "value": "\"RVA\\05472795790923\\0541772546900:01f7dcb7ca53925fef6c580bf6dd0c1e5e45e6ff4703faf44c5b79fbf0e8c8b5e6f96eb9\"", "path": "/", "domain": ".instagram.com", "secure": true, "httpOnly": true, "sameSite": "Lax"}, {"name": "ds_user_id", "value": "72795790923", "path": "/", "domain": ".instagram.com", "secure": true, "httpOnly": false, "expiry": 1748786900, "sameSite": "None"}]